dotpath/__init__.py
dotpath-1.0.0.dist-info/METADATA
dotpath-1.0.0.dist-info/WHEEL
dotpath-1.0.0.dist-info/RECORD
