Metadata-Version: 2.4
Name: dotpath
Version: 1.0.0
Summary: A module to access Python props using dotpath.
Project-URL: Documentation, https://dotpath.readthedocs.io/en/latest
Project-URL: Repository, https://github.com/silasvasconcelos/dotpath
Project-URL: Homepage, https://github.com/silasvasconcelos/dotpath
Project-URL: Issues, https://github.com/silasvasconcelos/dotpath/issues
Author-email: Silas Vasconcelos <silasvasconcelos@hotmail.com.br>
License: MIT
Keywords: helper,utils
Classifier: Development Status :: 4 - Beta
Classifier: Intended Audience :: Developers
Classifier: License :: OSI Approved :: MIT License
Classifier: Programming Language :: Python
Classifier: Programming Language :: Python :: 3
Classifier: Programming Language :: Python :: 3 :: Only
Classifier: Programming Language :: Python :: 3.8
Classifier: Programming Language :: Python :: 3.9
Classifier: Programming Language :: Python :: 3.10
Classifier: Programming Language :: Python :: 3.11
Classifier: Programming Language :: Python :: 3.12
Classifier: Programming Language :: Python :: 3.13
Classifier: Programming Language :: Python :: 3.14
Classifier: Topic :: Software Development :: Libraries
Classifier: Topic :: Utilities
Requires-Python: >=3.8
